izio_cli/__init__.py
izio_cli/cli.py
izio_cli/helper/__init__.py
izio_cli/helper/console_helper.py
izio_cli/helper/console_validators.py
izio_cli/helper/fs_helper.py
izio_cli/helper/loyalty_helper.py
izio_cli/helper/pattern_helper.py
izio_cli/helper/project_helper.py
izio_cli/helper/strings_transformers.py
izio_cli/pattern/__init__.py
izio_cli/pattern/dot_net_pattern.py
izio_cli/pattern/flutter_pattern.py
izio_cli/values/__init__.py
izio_cli/values/dot_net_payload.py
izio_cli/values/flutter_payloads.py
izio_cli-0.2.63.dist-info/LICENSE
izio_cli-0.2.63.dist-info/METADATA
izio_cli-0.2.63.dist-info/WHEEL
izio_cli-0.2.63.dist-info/entry_points.txt
izio_cli-0.2.63.dist-info/RECORD
