Metadata-Version: 2.1
Name: izio-cli
Version: 0.2.63
Summary: Izio CLI is a comprehensive command-line interface tool designed to facilitate the management and automation of various aspects of Izio&Co software development projects.
License: Beerware
Author: saulopef
Author-email: saulopef@gmail.com
Requires-Python: >=3.12,<3.13
Classifier: Development Status :: 3 - Alpha
Classifier: Environment :: Console
Classifier: Intended Audience :: Developers
Classifier: License :: Other/Proprietary License
Classifier: Operating System :: OS Independent
Classifier: Programming Language :: Python :: 3
Classifier: Programming Language :: Python :: 3.12
Requires-Dist: inquirer (>=3.2.3,<4.0.0)
Requires-Dist: rich (>=13.7.0,<14.0.0)
Requires-Dist: typer (>=0.9.0,<0.10.0)
